pytest_camel_collect/__init__.py
pytest_camel_collect/plugin.py
pytest_camel_collect/version.py
pytest_camel_collect-1.0.2.dist-info/LICENSE.txt
pytest_camel_collect-1.0.2.dist-info/METADATA
pytest_camel_collect-1.0.2.dist-info/WHEEL
pytest_camel_collect-1.0.2.dist-info/entry_points.txt
pytest_camel_collect-1.0.2.dist-info/top_level.txt
pytest_camel_collect-1.0.2.dist-info/RECORD
