Metadata-Version: 2.1
Name: pytest-camel-collect
Version: 1.0.2
Summary: Enable CamelCase-aware pytest class collection
Home-page: https://github.com/theY4Kman/pytest-camel-collect
Author: Zach "theY4Kman" Kanzler
Author-email: they4kman@gmail.com
License: UNKNOWN
Platform: UNKNOWN
Classifier: Framework :: Pytest
Requires-Python: >=3.6
Requires-Dist: pytest (>=2.9)
Requires-Dist: inflection (<0.4,>=0.3.1)
Provides-Extra: dev
Requires-Dist: pytest-camel-collect[test] ; extra == 'dev'
Requires-Dist: twine (~=1.12.1) ; extra == 'dev'
Provides-Extra: test
Requires-Dist: pytest-lambda (==0.0.2) ; extra == 'test'
Requires-Dist: tox (~=3.18) ; extra == 'test'
